nbox.py
nboxes-0.0.2.dist-info/LICENSE
nboxes-0.0.2.dist-info/METADATA
nboxes-0.0.2.dist-info/WHEEL
nboxes-0.0.2.dist-info/top_level.txt
nboxes-0.0.2.dist-info/RECORD
