Metadata-Version: 2.1
Name: nboxes
Version: 0.0.2
Summary: How to put n boxes into a rectangle area.
Home-page: UNKNOWN
Author: Summer Fang
License: UNKNOWN
Platform: UNKNOWN
Classifier: Programming Language :: Python :: 3
Classifier: License :: OSI Approved :: MIT License
Classifier: Operating System :: OS Independent
Requires-Python: >=3.6
